uv_pack/__init__.py
uv_pack/_build.py
uv_pack/_download.py
uv_pack/_export.py
uv_pack/_files.py
uv_pack/_logging.py
uv_pack/_process.py
uv_pack/_python.py
uv_pack/_scripts.py
uv_pack/py.typed
uv_pack/scripts/README.md
uv_pack/scripts/SPEC.md
uv_pack/scripts/unpack.cmd
uv_pack/scripts/unpack.ps1
uv_pack/scripts/unpack.sh
uv_pack-0.1.0.dist-info/WHEEL
uv_pack-0.1.0.dist-info/entry_points.txt
uv_pack-0.1.0.dist-info/METADATA
uv_pack-0.1.0.dist-info/RECORD
