Metadata-Version: 2.3
Name: uv-pack
Version: 0.1.0
Summary: Pack you uv environment for offline usage.
Author: David Muhr
Author-email: David Muhr <muhrdavid+github@gmail.com>
Classifier: Development Status :: 3 - Alpha
Classifier: License :: OSI Approved :: MIT License
Classifier: Topic :: Software Development :: Libraries
Classifier: Topic :: Scientific/Engineering
Classifier: Topic :: Utilities
Classifier: Intended Audience :: Developers
Classifier: Intended Audience :: Science/Research
Classifier: Intended Audience :: Education
Classifier: Programming Language :: Python :: 3.10
Classifier: Programming Language :: Python :: 3.11
Classifier: Programming Language :: Python :: 3.12
Classifier: Programming Language :: Python :: 3.13
Classifier: Programming Language :: Python :: 3 :: Only
Classifier: Operating System :: Microsoft :: Windows
Classifier: Operating System :: POSIX
Classifier: Operating System :: Unix
Classifier: Operating System :: MacOS
Classifier: Typing :: Typed
Requires-Dist: packaging>=24.0
Requires-Dist: requests>=2
Requires-Dist: typer>=0.19
Requires-Python: >=3.10
